twitter_client_py/__init__.py
twitter_client_py/async_twitter_client.py
twitter_client_py/rate_limit.py
twitter_client_py/twitter_client.py
twitter_client_py-0.3.3.dist-info/LICENSE
twitter_client_py-0.3.3.dist-info/METADATA
twitter_client_py-0.3.3.dist-info/WHEEL
twitter_client_py-0.3.3.dist-info/top_level.txt
twitter_client_py-0.3.3.dist-info/RECORD
