Metadata-Version: 2.1
Name: twitter-client-py
Version: 0.3.3
Summary: Python client for interacting with Twitter V2 API available at https://rapidapi.com/datarise-datarise-default/api/twitter-x
Author: Omar MHAIMDAT
Author-email: Omar MHAIMDAT <omarmhaimdat@gmail.com>
License: (The MIT License)
Project-URL: homepage, https://github.com/datarise-org-ma/twitter-client-py
Project-URL: repository, https://github.com/datarise-org-ma/twitter-client-py
Project-URL: documentation, https://github.com/datarise-org-ma/twitter-client-py/blob/main/README.md
Project-URL: issues, https://github.com/datarise-org-ma/twitter-client-py/issues
Keywords: twitter,api,client,v2
Classifier: Intended Audience :: Developers
Classifier: License :: OSI Approved :: MIT License
Classifier: Programming Language :: Python :: 3
Classifier: Programming Language :: Python :: 3.7
Classifier: Programming Language :: Python :: 3.8
Classifier: Programming Language :: Python :: 3.9
Classifier: Programming Language :: Python :: 3.10
Classifier: Programming Language :: Python :: 3.11
Classifier: Programming Language :: Python :: 3.12
Classifier: Programming Language :: Python :: 3 :: Only
Classifier: Topic :: Software Development :: Libraries
Classifier: Topic :: Software Development :: Libraries :: Python Modules
Requires-Python: >=3.7
License-File: LICENSE
Requires-Dist: aiohttp
Requires-Dist: requests
